[
    {
        "Country,2023":"United States,\"27,720.73\""
    },
    {
        "Country,2023":"China,\"17,758.05\""
    },
    {
        "Country,2023":"Germany,\"4,527.01\""
    },
    {
        "Country,2023":"Japan,\"4,219.83\""
    },
    {
        "Country,2023":"India,\"3,567.55\""
    },
    {
        "Country,2023":"United Kingdom,\"3,382.12\""
    },
    {
        "Country,2023":"France,\"3,052.71\""
    },
    {
        "Country,2023":"Italy,\"2,301.60\""
    },
    {
        "Country,2023":"Brazil,\"2,173.67\""
    },
    {
        "Country,2023":"Canada,\"2,142.47\""
    },
    {
        "Country,2023":"Russia,\"2,009.96\""
    },
    {
        "Country,2023":"Korea,\"1,839.06\""
    },
    {
        "Country,2023":"Mexico,\"1,788.82\""
    },
    {
        "Country,2023":"Australia,\"1,740.62\""
    },
    {
        "Country,2023":"Spain,\"1,620.56\""
    },
    {
        "Country,2023":"Indonesia,\"1,371.17\""
    },
    {
        "Country,2023":"Netherlands,\"1,154.69\""
    },
    {
        "Country,2023":"T\u30fbrkiye,\"1,129.97\""
    },
    {
        "Country,2023":"Saudi Arabia,\"1,067.58\""
    },
    {
        "Country,2023":"Switzerland,894.811"
    },
    {
        "Country,2023":"Poland,811.736"
    },
    {
        "Country,2023":"Taiwan Province of China,755.674"
    },
    {
        "Country,2023":"Argentina,645.511"
    },
    {
        "Country,2023":"Belgium,632.399"
    },
    {
        "Country,2023":"Sweden,584.914"
    },
    {
        "Country,2023":"Ireland,551.554"
    },
    {
        "Country,2023":"Austria,517.662"
    },
    {
        "Country,2023":"Thailand,514.836"
    },
    {
        "Country,2023":"United Arab Emirates,514.13"
    },
    {
        "Country,2023":"Israel,513.611"
    },
    {
        "Country,2023":"Singapore,501.428"
    },
    {
        "Country,2023":"Norway,485.311"
    },
    {
        "Country,2023":"Bangladesh,451.534"
    },
    {
        "Country,2023":"Philippines,437.146"
    },
    {
        "Country,2023":"Vietnam,433.702"
    },
    {
        "Country,2023":"Denmark,407.092"
    },
    {
        "Country,2023":"Malaysia,399.705"
    },
    {
        "Country,2023":"Egypt,393.828"
    },
    {
        "Country,2023":"Hong Kong SAR,380.812"
    },
    {
        "Country,2023":"South Africa,380.592"
    },
    {
        "Country,2023":"Islamic Republic of Iran,372.82"
    },
    {
        "Country,2023":"Nigeria,363.816"
    },
    {
        "Country,2023":"Colombia,363.57"
    },
    {
        "Country,2023":"Romania,351.074"
    },
    {
        "Country,2023":"Czech Republic,343.208"
    },
    {
        "Country,2023":"Pakistan,337.457"
    },
    {
        "Country,2023":"Chile,335.642"
    },
    {
        "Country,2023":"Finland,295.618"
    },
    {
        "Country,2023":"Portugal,287.187"
    },
    {
        "Country,2023":"Peru,266.912"
    },
    {
        "Country,2023":"Kazakhstan,263.372"
    },
    {
        "Country,2023":"Iraq,252.407"
    },
    {
        "Country,2023":"New Zealand,248.687"
    },
    {
        "Country,2023":"Algeria,240.064"
    },
    {
        "Country,2023":"Greece,238.275"
    },
    {
        "Country,2023":"Qatar,213.003"
    },
    {
        "Country,2023":"Hungary,212.464"
    },
    {
        "Country,2023":"Ukraine,178.34"
    },
    {
        "Country,2023":"Kuwait,163.716"
    },
    {
        "Country,2023":"Ethiopia,159.747"
    },
    {
        "Country,2023":"Morocco,144.438"
    },
    {
        "Country,2023":"Slovak Republic,132.832"
    },
    {
        "Country,2023":"Dominican Republic,121.785"
    },
    {
        "Country,2023":"Ecuador,118.845"
    },
    {
        "Country,2023":"Puerto Rico,117.902"
    },
    {
        "Country,2023":"Angola,109.678"
    },
    {
        "Country,2023":"Oman,108.811"
    },
    {
        "Country,2023":"Kenya,108.747"
    },
    {
        "Country,2023":"Guatemala,104.436"
    },
    {
        "Country,2023":"Bulgaria,101.611"
    },
    {
        "Country,2023":"Uzbekistan,101.584"
    },
    {
        "Country,2023":"Venezuela,99.203"
    },
    {
        "Country,2023":"Costa Rica,86.509"
    },
    {
        "Country,2023":"Luxembourg,85.78"
    },
    {
        "Country,2023":"Panama,83.382"
    },
    {
        "Country,2023":"Croatia,82.711"
    },
    {
        "Country,2023":"Tanzania,79.138"
    },
    {
        "Country,2023":"C\u30fbte d'Ivoire,78.887"
    },
    {
        "Country,2023":"Lithuania,77.844"
    },
    {
        "Country,2023":"Turkmenistan,77.716"
    },
    {
        "Country,2023":"Uruguay,77.241"
    },
    {
        "Country,2023":"Ghana,76.402"
    },
    {
        "Country,2023":"Serbia,75.187"
    },
    {
        "Country,2023":"Azerbaijan,72.356"
    },
    {
        "Country,2023":"Belarus,71.792"
    },
    {
        "Country,2023":"Slovenia,69.168"
    },
    {
        "Country,2023":"Democratic Republic of the Congo,66.923"
    },
    {
        "Country,2023":"Myanmar,64.505"
    },
    {
        "Country,2023":"Uganda,51.093"
    },
    {
        "Country,2023":"Jordan,50.885"
    },
    {
        "Country,2023":"Cameroon,49.287"
    },
    {
        "Country,2023":"Tunisia,48.541"
    },
    {
        "Country,2023":"Macao SAR,47.061"
    },
    {
        "Country,2023":"Bahrain,46.08"
    },
    {
        "Country,2023":"Bolivia,45.468"
    },
    {
        "Country,2023":"Libya,43.958"
    },
    {
        "Country,2023":"Latvia,43.64"
    },
    {
        "Country,2023":"Cambodia,43.304"
    },
    {
        "Country,2023":"Paraguay,42.955"
    },
    {
        "Country,2023":"Estonia,41.297"
    },
    {
        "Country,2023":"Nepal,40.907"
    },
    {
        "Country,2023":"Sudan,38.109"
    },
    {
        "Country,2023":"Zimbabwe,35.231"
    },
    {
        "Country,2023":"Honduras,34.229"
    },
    {
        "Country,2023":"El Salvador,34.016"
    },
    {
        "Country,2023":"Cyprus,32.239"
    },
    {
        "Country,2023":"Iceland,31.325"
    },
    {
        "Country,2023":"Senegal,30.937"
    },
    {
        "Country,2023":"Papua New Guinea,30.926"
    },
    {
        "Country,2023":"Georgia,30.536"
    },
    {
        "Country,2023":"Zambia,28.163"
    },
    {
        "Country,2023":"Trinidad and Tobago,28.024"
    },
    {
        "Country,2023":"Bosnia and Herzegovina,27.055"
    },
    {
        "Country,2023":"Armenia,24.086"
    },
    {
        "Country,2023":"Lebanon,24.023"
    },
    {
        "Country,2023":"Guinea,23.005"
    },
    {
        "Country,2023":"Albania,22.822"
    },
    {
        "Country,2023":"Malta,22.335"
    },
    {
        "Country,2023":"Mozambique,20.958"
    },
    {
        "Country,2023":"Mongolia,20.315"
    },
    {
        "Country,2023":"Burkina Faso,20.283"
    },
    {
        "Country,2023":"Mali,20.21"
    },
    {
        "Country,2023":"Gabon,20.059"
    },
    {
        "Country,2023":"Benin,19.679"
    },
    {
        "Country,2023":"Haiti,19.603"
    },
    {
        "Country,2023":"Botswana,19.396"
    },
    {
        "Country,2023":"Jamaica,19.315"
    },
    {
        "Country,2023":"Yemen,18.806"
    },
    {
        "Country,2023":"Nicaragua,17.843"
    },
    {
        "Country,2023":"Chad,17.605"
    },
    {
        "Country,2023":"West Bank and Gaza,17.421"
    },
    {
        "Country,2023":"Afghanistan,17.329"
    },
    {
        "Country,2023":"Guyana,17.05"
    },
    {
        "Country,2023":"Niger,16.809"
    },
    {
        "Country,2023":"Moldova,16.576"
    },
    {
        "Country,2023":"Madagascar,15.79"
    },
    {
        "Country,2023":"Brunei Darussalam,15.126"
    },
    {
        "Country,2023":"Lao P.D.R.,14.943"
    },
    {
        "Country,2023":"North Macedonia,14.769"
    },
    {
        "Country,2023":"Mauritius,14.557"
    },
    {
        "Country,2023":"The Bahamas,14.338"
    },
    {
        "Country,2023":"Republic of Congo,14.169"
    },
    {
        "Country,2023":"Rwanda,14.097"
    },
    {
        "Country,2023":"Kyrgyz Republic,13.993"
    },
    {
        "Country,2023":"Malawi,12.674"
    },
    {
        "Country,2023":"Namibia,12.345"
    },
    {
        "Country,2023":"Equatorial Guinea,11.975"
    },
    {
        "Country,2023":"Tajikistan,11.855"
    },
    {
        "Country,2023":"Somalia,10.969"
    },
    {
        "Country,2023":"Mauritania,10.649"
    },
    {
        "Country,2023":"Kosovo,10.44"
    },
    {
        "Country,2023":"Togo,9.081"
    },
    {
        "Country,2023":"Montenegro,7.406"
    },
    {
        "Country,2023":"South Sudan,7.178"
    },
    {
        "Country,2023":"Barbados,6.721"
    },
    {
        "Country,2023":"Maldives,6.573"
    },
    {
        "Country,2023":"Sierra Leone,6.397"
    },
    {
        "Country,2023":"Fiji,5.442"
    },
    {
        "Country,2023":"Eswatini,4.856"
    },
    {
        "Country,2023":"Liberia,4.39"
    },
    {
        "Country,2023":"Burundi,4.241"
    },
    {
        "Country,2023":"Djibouti,4.011"
    },
    {
        "Country,2023":"Aruba,3.945"
    },
    {
        "Country,2023":"Suriname,3.747"
    },
    {
        "Country,2023":"Andorra,3.728"
    },
    {
        "Country,2023":"Belize,3.069"
    },
    {
        "Country,2023":"Bhutan,2.908"
    },
    {
        "Country,2023":"Central African Republic,2.631"
    },
    {
        "Country,2023":"Cabo Verde,2.588"
    },
    {
        "Country,2023":"St. Lucia,2.43"
    },
    {
        "Country,2023":"Timor-Leste,2.379"
    },
    {
        "Country,2023":"The Gambia,2.361"
    },
    {
        "Country,2023":"Lesotho,2.211"
    },
    {
        "Country,2023":"Seychelles,2.141"
    },
    {
        "Country,2023":"Antigua and Barbuda,2.044"
    },
    {
        "Country,2023":"Guinea-Bissau,2.005"
    },
    {
        "Country,2023":"San Marino,1.988"
    },
    {
        "Country,2023":"Solomon Islands,1.633"
    },
    {
        "Country,2023":"Comoros,1.34"
    },
    {
        "Country,2023":"Grenada,1.324"
    },
    {
        "Country,2023":"Vanuatu,1.123"
    },
    {
        "Country,2023":"St. Vincent and the Grenadines,1.083"
    },
    {
        "Country,2023":"St. Kitts and Nevis,1.056"
    },
    {
        "Country,2023":"Samoa,0.934"
    },
    {
        "Country,2023":"S\u30fbo Tom\u30fb and Pr\u30fbncipe,0.684"
    },
    {
        "Country,2023":"Dominica,0.654"
    },
    {
        "Country,2023":"Tonga,0.52"
    },
    {
        "Country,2023":"Micronesia,0.46"
    },
    {
        "Country,2023":"Palau,0.282"
    },
    {
        "Country,2023":"Kiribati,0.279"
    },
    {
        "Country,2023":"Marshall Islands,0.259"
    },
    {
        "Country,2023":"Nauru,0.154"
    },
    {
        "Country,2023":"Tuvalu,0.068"
    }
]